mlxplain/__init__.py
mlxplain/explainers/tabular/__init__.py
mlxplain/explainers/tabular/specific/__init__.py
mlxplain/explainers/tabular/specific/dimlpfidex.py
mlxplain/explainers/vision/__init__.py
mlxplain/explainers/vision/specific/__init__.py
mlxplain/explainers/vision/specific/rulesextract.py
mlxplain/explanations/__init__.py
mlxplain/explanations/images/__init__.py
mlxplain/explanations/images/rules.py
mlxplain/explanations/tabular/dimlpfidex.py
mlxplain-1.0.4.dist-info/METADATA
mlxplain-1.0.4.dist-info/WHEEL
mlxplain-1.0.4.dist-info/licenses/LICENSE
mlxplain-1.0.4.dist-info/RECORD
