Metadata-Version: 2.3
Name: mlxplain
Version: 1.0.4
Summary: An open platform for accelerating the development of eXplainable AI systems
Author-email: Arthur Babey <arthur.babey@heig-vd.ch>, Jean-Marc Boutay <jean-marc.boutay@heige.ch>, Rémy Marquis <remy.marquis@heig-vd.ch>
License: 3-Clause BSD License
License-File: LICENSE
Keywords: machine learning,xai
Classifier: Intended Audience :: Developers
Classifier: Intended Audience :: Education
Classifier: Intended Audience :: Science/Research
Classifier: License :: OSI Approved :: BSD License
Classifier: Operating System :: MacOS
Classifier: Operating System :: Microsoft :: Windows
Classifier: Operating System :: POSIX
Classifier: Operating System :: Unix
Classifier: Programming Language :: Python :: 3
Classifier: Topic :: Scientific/Engineering
Classifier: Topic :: Scientific/Engineering :: Artificial Intelligence
Classifier: Topic :: Scientific/Engineering :: Mathematics
Requires-Python: >=3.9.0
Requires-Dist: black>=24.4.2
Requires-Dist: build>=1.0.3
Requires-Dist: coverage>=7.5.4
Requires-Dist: dash-bootstrap-components>=1.6.0
Requires-Dist: dash>=2.17.1
Requires-Dist: flake8>=7.1.0
Requires-Dist: jupyter-dash>=0.4.2
Requires-Dist: omnixai-community>=1.3.2.2
Requires-Dist: pre-commit>=3.7.1
Requires-Dist: rules-extraction>=0.1.1
Requires-Dist: sphinx-autodoc-typehints>=1.25.3
Requires-Dist: sphinx-rtd-theme>=1.3.0
Requires-Dist: sphinx>=6.2.1
Requires-Dist: torch>=2.4.0
Requires-Dist: torchvision>=0.19.0
